Metadata-Version: 2.1
Name: qualysN
Version: 0.1.0
Summary: My first Python library
Author: Chris Nam
License: MIT
License-File: LICENSE.txt
